[
    {
      "Accession Number": "2024.2.0016",
      "Description": "Blue/red/yellow kente wrap",
      "Media": "Polyester, cotton, steel",
      "Textile": "",
      "City Code": "DUD",
      "Construction": "Machine-stiched",
      "Archive Tag": "0016",
      "Brand Tag": "None",
      "Year": 2024,
      "Collection Code": 2
    },
    {
      "Accession Number": "2024.2.0017",
      "Description": "Reworked kimono",
      "Media": "Silk, Cotton",
      "Textile": "",
      "City Code": "DUD",
      "Construction": "Hand-stiched",
      "Archive Tag": "0017",
      "Brand Tag": "None",
      "Year": 2024,
      "Collection Code": 2
    },
    {
      "Accession Number": "2024.2.0018",
      "Description": "Navy wrap skirt",
      "Media": "Meisen, silk, cotton",
      "Textile": "",
      "City Code": "DUD",
      "Construction": "Hand-stiched, Machine-stiched mainseams",
      "Archive Tag": "0018",
      "Brand Tag": "None",
      "Year": 2024,
      "Collection Code": 2
    },
    {
      "Accession Number": "2024.2.0019",
      "Description": "Gathered birectangular sleeveless blouse",
      "Media": "Polyester, cotton",
      "Textile": "",
      "City Code": "DUD",
      "Construction": "Hand-stiched, Machine-stiched mainseams",
      "Archive Tag": "0019",
      "Brand Tag": "None",
      "Year": 2024,
      "Collection Code": 2
    },
    {
      "Accession Number": "2019.1.0011",
      "Description": "Waist pleated blouse",
      "Media": "Unknown fibres",
      "Textile": "",
      "City Code": "CHC",
      "Construction": "Machine-stiched",
      "Archive Tag": "0011",
      "Brand Tag": "NEL_0011",
      "Year": 2019,
      "Collection Code": 1
    },
    {
      "Accession Number": "2019.1.0012",
      "Description": "Waist pleated blouse 2",
      "Media": "Unknown fibre",
      "Textile": "",
      "City Code": "CHC",
      "Construction": "Machine-stiched",
      "Archive Tag": "0012",
      "Brand Tag": "None",
      "Year": 2019,
      "Collection Code": 1
    },
    {
      "Accession Number": "2019.1.0015",
      "Description": "Pinstripe skirt, folded draped waistband",
      "Media": "Cotton, synthetic interfacing",
      "Textile": "",
      "City Code": "CHC",
      "Construction": "Machine-stiched",
      "Archive Tag": "0015",
      "Brand Tag": "None",
      "Year": 2019,
      "Collection Code": 1
    },
    {
      "Accession Number": "2023.3.0014",
      "Description": "Reworked haori",
      "Media": "Meisen, silk",
      "Textile": "",
      "City Code": "DUD",
      "Construction": "Hand-stiched",
      "Archive Tag": "0014",
      "Brand Tag": "None",
      "Year": 2023,
      "Collection Code": 3
    },
    {
      "Accession Number": "..",
      "Description": "",
      "Media": "",
      "Textile": "",
      "City Code": "",
      "Construction": "",
      "Archive Tag": "",
      "Brand Tag": "",
      "Year": null,
      "Collection Code": null
    },
    {
      "Accession Number": "..",
      "Description": "",
      "Media": "",
      "Textile": "",
      "City Code": "",
      "Construction": "",
      "Archive Tag": "",
      "Brand Tag": "",
      "Year": null,
      "Collection Code": null
    }
   ]