[
    {
      "accessionNumber": "2024.2.0016",
      "description": "Blue/red/yellow kente wrap",
      "media": "Polyester, cotton, steel",
      "textile": "",
      "cityCode": "DUD",
      "construction": "Machine-stiched",
      "archiveTag": "0016",
      "brandTag": "None",
      "year": 2024,
      "collectionCode": 2
    },
    {
      "accessionNumber": "2024.2.0017",
      "description": "Reworked kimono",
      "media": "Silk, Cotton",
      "textile": "",
      "cityCode": "DUD",
      "construction": "Hand-stiched",
      "archiveTag": "0017",
      "brandTag": "None",
      "year": 2024,
      "collectionCode": 2
    },
    {
      "accessionNumber": "2024.2.0018",
      "description": "Navy wrap skirt",
      "media": "Meisen, silk, cotton",
      "textile": "",
      "cityCode": "DUD",
      "construction": "Hand-stiched, Machine-stiched mainseams",
      "archiveTag": "0018",
      "brandTag": "None",
      "year": 2024,
      "collectionCode": 2
    },
    {
      "accessionNumber": "2024.2.0019",
      "description": "Gathered birectangular sleeveless blouse",
      "media": "Polyester, cotton",
      "textile": "",
      "cityCode": "DUD",
      "construction": "Hand-stiched, Machine-stiched mainseams",
      "archiveTag": "0019",
      "brandTag": "None",
      "year": 2024,
      "collectionCode": 2
    },
    {
      "accessionNumber": "2019.1.0011",
      "description": "Waist pleated blouse",
      "media": "Unknown fibres",
      "textile": "",
      "cityCode": "CHC",
      "construction": "Machine-stiched",
      "archiveTag": "0011",
      "brandTag": "NEL_0011",
      "year": 2019,
      "collectionCode": 1
    },
    {
      "accessionNumber": "2019.1.0012",
      "description": "Waist pleated blouse 2",
      "media": "Unknown fibre",
      "textile": "",
      "cityCode": "CHC",
      "construction": "Machine-stiched",
      "archiveTag": "0012",
      "brandTag": "None",
      "year": 2019,
      "collectionCode": 1
    },
    {
      "accessionNumber": "2019.1.0015",
      "description": "Pinstripe skirt, folded draped waistband",
      "media": "Cotton, synthetic interfacing",
      "textile": "",
      "cityCode": "CHC",
      "construction": "Machine-stiched",
      "archiveTag": "0015",
      "brandTag": "None",
      "year": 2019,
      "collectionCode": 1
    },
    {
      "accessionNumber": "2023.3.0014",
      "description": "Reworked haori",
      "media": "Meisen, silk",
      "textile": "",
      "cityCode": "DUD",
      "construction": "Hand-stiched",
      "archiveTag": "0014",
      "brandTag": "None",
      "year": 2023,
      "collectionCode": 3
    },
    {
      "accessionNumber": "..",
      "description": "",
      "media": "",
      "textile": "",
      "cityCode": "",
      "construction": "",
      "archiveTag": "",
      "brandTag": "",
      "year": 0,
      "collectionCode": 0
    },
    {
      "accessionNumber": "..",
      "description": "",
      "media": "",
      "textile": "",
      "cityCode": "",
      "construction": "",
      "archiveTag": "",
      "brandTag": "",
      "year": 0,
      "collectionCode": 0
    }
   ]
